clean_graph/__init__.py
clean_graph/clean_graph.py
clean_graph/columnchartwithwaterfall.py
clean_graph/general_functions.py
clean_graph/multiplier.py
clean_graph-0.1.1.dist-info/AUTHORS.rst
clean_graph-0.1.1.dist-info/LICENSE
clean_graph-0.1.1.dist-info/METADATA
clean_graph-0.1.1.dist-info/WHEEL
clean_graph-0.1.1.dist-info/top_level.txt
clean_graph-0.1.1.dist-info/RECORD
