Metadata-Version: 2.1
Name: clean-graph
Version: 0.1.1
Summary: Clean Graph was a Python package for IBCS-like graphs based on matplotlib. This package will no longer be maintained and has been replaced by 'Clean Business Chart', with pandas support.
Home-page: https://github.com/marcelw1323/clean_graph
Author: Marcel Wuijtenburg
Author-email: marcelw1323@gmail.com
License: MIT license
Keywords: clean_graph
Classifier: Development Status :: 2 - Pre-Alpha
Classifier: Intended Audience :: Developers
Classifier: License :: OSI Approved :: MIT License
Classifier: Natural Language :: English
Classifier: Programming Language :: Python :: 3
Classifier: Programming Language :: Python :: 3.6
Classifier: Programming Language :: Python :: 3.7
Classifier: Programming Language :: Python :: 3.8
Requires-Python: >=3.6
License-File: LICENSE
License-File: AUTHORS.rst
Requires-Dist: matplotlib (>=3.5.1)
